pygh/__init__.py
pygh/art.py
pygh-0.1.0a1.dist-info/LICENSE
pygh-0.1.0a1.dist-info/METADATA
pygh-0.1.0a1.dist-info/WHEEL
pygh-0.1.0a1.dist-info/top_level.txt
pygh-0.1.0a1.dist-info/RECORD
