Metadata-Version: 2.1
Name: pygh
Version: 0.1.0a1
Summary: UNKNOWN
Home-page: http://github.com/fourlight/pygh
Author: Jiachen Zou
Author-email: 873039943@QQ.com
License: UNKNOWN
Platform: UNKNOWN
Classifier: License :: OSI Approved :: MIT License
Classifier: Programming Language :: Python :: 2
Classifier: Programming Language :: Python :: 3
Classifier: Programming Language :: Python :: 3.6
Classifier: Programming Language :: Python :: 3.7
Classifier: Programming Language :: Python :: 3.8
Classifier: Programming Language :: Python :: 3.9
Classifier: Natural Language :: Chinese (Simplified)
Classifier: Topic :: Scientific/Engineering :: Visualization
License-File: LICENSE
Requires-Dist: jieba (==0.42.1)
Requires-Dist: pyecharts (==1.9.0)
